async_cron/__init__.py
async_cron/job.py
async_cron/job_loader.py
async_cron/logger.py
async_cron/schedule.py
async_cron/units.py
async_cron-1.6.2.dist-info/LICENSE
async_cron-1.6.2.dist-info/METADATA
async_cron-1.6.2.dist-info/WHEEL
async_cron-1.6.2.dist-info/top_level.txt
async_cron-1.6.2.dist-info/RECORD
