Metadata-Version: 2.1
Name: async-cron
Version: 1.6.2
Summary: asyncio crontab utils
Home-page: https://github.com/aohan237/async_cron
Author: aohan237
Author-email: aohan237@gmail.com
License: MIT
Platform: POSIX
Classifier: License :: OSI Approved :: MIT License
Classifier: Development Status :: 4 - Beta
Classifier: Programming Language :: Python
Classifier: Programming Language :: Python :: 3
Classifier: Programming Language :: Python :: 3.4
Classifier: Programming Language :: Python :: 3.5
Classifier: Programming Language :: Python :: 3.6
Classifier: Operating System :: POSIX
Classifier: Environment :: Web Environment
Classifier: Intended Audience :: Developers
Classifier: Topic :: Software Development
Classifier: Topic :: Software Development :: Libraries
Requires-Dist: arrow
